{"stats": "openaigym.episode_batch.0.13716.stats.json", "videos": [["openaigym.video.0.13716.video000000.mp4", "openaigym.video.0.13716.video000000.meta.json"], ["openaigym.video.0.13716.video000400.mp4", "openaigym.video.0.13716.video000400.meta.json"], ["openaigym.video.0.13716.video000800.mp4", "openaigym.video.0.13716.video000800.meta.json"], ["openaigym.video.0.13716.video001200.mp4", "openaigym.video.0.13716.video001200.meta.json"], ["openaigym.video.0.13716.video001600.mp4", "openaigym.video.0.13716.video001600.meta.json"], ["openaigym.video.0.13716.video002000.mp4", "openaigym.video.0.13716.video002000.meta.json"]], "env_info": {"gym_version": "0.15.4", "env_id": "CartPole-v0"}}